reclearn/__init__.py
reclearn/data/__init__.py
reclearn/data/feature_column.py
reclearn/data/utils.py
reclearn/data/datasets/__init__.py
reclearn/data/datasets/beauty.py
reclearn/data/datasets/criteo.py
reclearn/data/datasets/games.py
reclearn/data/datasets/movielens.py
reclearn/data/datasets/steam.py
reclearn/evaluator/__init__.py
reclearn/evaluator/evaluator.py
reclearn/evaluator/metrics.py
reclearn/layers/__init__.py
reclearn/layers/core.py
reclearn/layers/utils.py
reclearn/models/__init__.py
reclearn/models/losses.py
reclearn/models/matching/__init__.py
reclearn/models/matching/attrec.py
reclearn/models/matching/bpr.py
reclearn/models/matching/caser.py
reclearn/models/matching/dssm.py
reclearn/models/matching/fissa.py
reclearn/models/matching/gru4rec.py
reclearn/models/matching/ncf.py
reclearn/models/matching/poprec.py
reclearn/models/matching/sasrec.py
reclearn/models/matching/youtubednn.py
reclearn/models/ranking/__init__.py
reclearn/models/ranking/afm.py
reclearn/models/ranking/dcn.py
reclearn/models/ranking/deep_crossing.py
reclearn/models/ranking/deepfm.py
reclearn/models/ranking/ffm.py
reclearn/models/ranking/fm.py
reclearn/models/ranking/nfm.py
reclearn/models/ranking/pnn.py
reclearn/models/ranking/wdl.py
reclearn/models/ranking/xdeepfm.py
reclearn-1.1.0.dist-info/LICENSE
reclearn-1.1.0.dist-info/METADATA
reclearn-1.1.0.dist-info/WHEEL
reclearn-1.1.0.dist-info/top_level.txt
reclearn-1.1.0.dist-info/RECORD
