Metadata-Version: 2.1
Name: reclearn
Version: 1.1.0
Summary: A simple package about learning recommendation
Home-page: https://github.com/ZiyaoGeng/RecLearn
Author: Ziyao Geng
Author-email: zggzy1996@163.com
License: MIT
Platform: UNKNOWN
Classifier: Programming Language :: Python :: 3
Classifier: License :: OSI Approved :: MIT License
Classifier: Operating System :: OS Independent
Requires-Python: >=3.8
License-File: LICENSE
